{
    "filename": "gloves-431_jpg.rf.b30a9a6a788e85903f07ec6b19d519b6.jpg",
    "detections": [
        {
            "label": "gloved_hand",
            "confidence": 0.9,
            "bbox": [
                22,
                67,
                190,
                414
            ]
        },
        {
            "label": "gloved_hand",
            "confidence": 0.86,
            "bbox": [
                219,
                67,
                402,
                414
            ]
        }
    ]
}